.editorconfig
.env
.gitignore
.travis.yml
LICENSE
MANIFEST.in
Pipfile
Pipfile.lock
README.md
docker-compose.yml
setup.py
tox.ini
brewblox_devcon_spark/__init__.py
brewblox_devcon_spark/__main__.py
brewblox_devcon_spark/broadcaster.py
brewblox_devcon_spark/commander.py
brewblox_devcon_spark/commander_sim.py
brewblox_devcon_spark/commands.py
brewblox_devcon_spark/communication.py
brewblox_devcon_spark/couchdb_client.py
brewblox_devcon_spark/datastore.py
brewblox_devcon_spark/device.py
brewblox_devcon_spark/exceptions.py
brewblox_devcon_spark/http_client.py
brewblox_devcon_spark/seeder.py
brewblox_devcon_spark/status.py
brewblox_devcon_spark/twinkeydict.py
brewblox_devcon_spark.egg-info/PKG-INFO
brewblox_devcon_spark.egg-info/SOURCES.txt
brewblox_devcon_spark.egg-info/dependency_links.txt
brewblox_devcon_spark.egg-info/requires.txt
brewblox_devcon_spark.egg-info/top_level.txt
brewblox_devcon_spark/api/__init__.py
brewblox_devcon_spark/api/alias_api.py
brewblox_devcon_spark/api/codec_api.py
brewblox_devcon_spark/api/debug_api.py
brewblox_devcon_spark/api/error_response.py
brewblox_devcon_spark/api/object_api.py
brewblox_devcon_spark/api/remote_api.py
brewblox_devcon_spark/api/savepoint_api.py
brewblox_devcon_spark/api/sse_api.py
brewblox_devcon_spark/api/system_api.py
brewblox_devcon_spark/api/utils.py
brewblox_devcon_spark/codec/__init__.py
brewblox_devcon_spark/codec/_path_extension.py
brewblox_devcon_spark/codec/codec.py
brewblox_devcon_spark/codec/compile.sh
brewblox_devcon_spark/codec/modifiers.py
brewblox_devcon_spark/codec/transcoders.py
brewblox_devcon_spark/codec/unit_conversion.py
brewblox_devcon_spark/codec/proto/.clang-format
brewblox_devcon_spark/codec/proto/ActuatorAnalogMock.proto
brewblox_devcon_spark/codec/proto/ActuatorDS2413.proto
brewblox_devcon_spark/codec/proto/ActuatorDigital.proto
brewblox_devcon_spark/codec/proto/ActuatorOffset.proto
brewblox_devcon_spark/codec/proto/ActuatorPin.proto
brewblox_devcon_spark/codec/proto/ActuatorPwm.proto
brewblox_devcon_spark/codec/proto/AnalogConstraints.proto
brewblox_devcon_spark/codec/proto/Balancer.proto
brewblox_devcon_spark/codec/proto/DS2413.proto
brewblox_devcon_spark/codec/proto/DigitalConstraints.proto
