Metadata-Version: 1.2
Name: brewblox-devcon-spark
Version: 0.5.0
Summary: Communication with Spark controllers
Home-page: https://github.com/BrewBlox/brewblox-devcon-spark
Author: BrewPi
Author-email: Development@brewpi.com
License: GPLv3
Keywords: brewing brewpi brewblox embedded controller spark service
Platform: UNKNOWN
Classifier: Development Status :: 4 - Beta
Classifier: License :: OSI Approved :: GNU General Public License (GPL)
Classifier: Operating System :: POSIX :: Linux
Classifier: Programming Language :: Python :: 3.7
Classifier: Framework :: AsyncIO
Classifier: Intended Audience :: End Users/Desktop
Classifier: Topic :: System :: Hardware
Requires-Python: >=3.7
